src/__init__.py
src/git_handler.py
src/main.py
src/pr_handler.py
src/template_handler.py
PRomancer-0.23.1.dist-info/METADATA
PRomancer-0.23.1.dist-info/WHEEL
PRomancer-0.23.1.dist-info/entry_points.txt
PRomancer-0.23.1.dist-info/top_level.txt
PRomancer-0.23.1.dist-info/RECORD
