Metadata-Version: 2.1
Name: PRomancer
Version: 0.23.1
Requires-Dist: openai <1.0,>=0.0
